ckb_textify/__init__.py
ckb_textify/app.py
ckb_textify/core/__init__.py
ckb_textify/core/pipeline.py
ckb_textify/core/tokenizer.py
ckb_textify/core/types.py
ckb_textify/modules/__init__.py
ckb_textify/modules/base.py
ckb_textify/modules/currency.py
ckb_textify/modules/date_time.py
ckb_textify/modules/diacritics.py
ckb_textify/modules/emojis.py
ckb_textify/modules/grammar.py
ckb_textify/modules/linguistics.py
ckb_textify/modules/math.py
ckb_textify/modules/numbers.py
ckb_textify/modules/phone.py
ckb_textify/modules/power.py
ckb_textify/modules/spacing.py
ckb_textify/modules/symbols.py
ckb_textify/modules/taggers.py
ckb_textify/modules/technical.py
ckb_textify/modules/transliteration.py
ckb_textify/modules/units.py
ckb_textify/modules/web.py
ckb_textify/resources/__init__.py
ckb_textify/resources/ali_k_map.py
ckb_textify/resources/dictionaries.py
ckb_textify/resources/emoji_map.py
ckb_textify/resources/patterns.py
ckb_textify/resources/transliteration_maps.py
ckb_textify/utils/__init__.py
ckb_textify/utils/detector.py
ckb_textify/utils/numbers.py
ckb_textify-5.0.1.dist-info/licenses/LICENSE
ckb_textify-5.0.1.dist-info/METADATA
ckb_textify-5.0.1.dist-info/WHEEL
ckb_textify-5.0.1.dist-info/top_level.txt
ckb_textify-5.0.1.dist-info/RECORD
