Metadata-Version: 2.4
Name: ckb-textify
Version: 5.0.1
Summary: Industrial-strength Text Normalization and Transliteration for Central Kurdish (Sorani)
Author-email: "Razwan M. Haji" <razwan.siktany778@gmail.com>
License: MIT License
Project-URL: Homepage, https://github.com/RazwanSiktany/ckb_textify
Project-URL: Live Demo, https://ckb-textify.streamlit.app/
Project-URL: Source Code, https://github.com/RazwanSiktany/ckb_textify
Project-URL: Issue Tracker, https://github.com/RazwanSiktany/ckb_textify/issues
Keywords: kurdish,sorani,normalization,transliteration,nlp,tts,text-processing,Central-Kurdish
Classifier: Programming Language :: Python :: 3
Classifier: License :: OSI Approved :: MIT License
Classifier: Operating System :: OS Independent
Classifier: Topic :: Text Processing :: Linguistic
Requires-Python: >=3.7
License-File: LICENSE
Requires-Dist: eng-to-ipa>=0.0.2
Requires-Dist: anyascii>=0.3.0
Provides-Extra: dev
Requires-Dist: pytest>=7.0; extra == "dev"
Requires-Dist: twine>=4.0; extra == "dev"
Requires-Dist: build>=0.10.0; extra == "dev"
Provides-Extra: app
Requires-Dist: streamlit>=1.20.0; extra == "app"
Dynamic: license-file
